{"ptx/3410notes.ptx": ["linear-algebra", "solutions-backmatter"], "ptx/chapter_vector_space.ptx": ["ch-vector-space"], "ptx/section_vsp_definition.ptx": ["sec-vec-sp"], "ptx/section_vsp_properties.ptx": ["sec-vsp-properties"], "ptx/section_subspace.ptx": ["sec-subspace"], "ptx/section_span.ptx": ["sec-span"], "ptx/worksheet-span.ptx": ["worksheet-span"], "ptx/section_independence.ptx": ["sec-independence"], "ptx/section_dimension.ptx": ["sec-dimension"], "ptx/section_sum.ptx": ["sec-subspace-combine"], "ptx/chapter_linear_transformations.ptx": ["ch-linear-trans"], "ptx/section_transform_intro.ptx": ["sec-lin-tran-intro"], "ptx/section_kernel_image.ptx": ["sec-kernel-image"], "ptx/section_isomorphism.ptx": ["sec-isomorphism"], "ptx/worksheet-transformation.ptx": ["worksheet-transformations"], "ptx/worksheet-recurrence.ptx": ["worksheet-recurrence"], "ptx/chapter_orthogonality.ptx": ["ch-orthogonality"], "ptx/section_ortho_sets.ptx": ["sec-orthogonal-sets"], "ptx/section_gram_schmidt.ptx": ["sec-gram-schmidt"], "ptx/section_ortho_proj.ptx": ["section-projection"], "ptx/worksheet-dual-basis.ptx": ["worksheet-dual-basis"], "ptx/worksheet-least-squares.ptx": ["worksheet-least-squares"], "ptx/chapter_diagonalization.ptx": ["ch-diagonalization"], "ptx/section_eigen_intro.ptx": ["sec-eigen-basics"], "ptx/section_diagonalization.ptx": ["subsec-ortho-diag"], "ptx/section_quadratic.ptx": ["sec-quadratic"], "ptx/section_complex_diag.ptx": ["sec-complex"], "ptx/worksheet-dynamical.ptx": ["worksheet-dynamical"], "ptx/section_matrix_factor.ptx": ["section-matrix-factor"], "ptx/worksheet-svd.ptx": ["worksheet-svd"], "ptx/chapter_change_basis.ptx": ["ch-change-basis"], "ptx/section_transf_matrix.ptx": ["sec-matrix-of-transformation"], "ptx/section_operator_matrix.ptx": ["sec-matrix-operator"], "ptx/section_direct_sum.ptx": ["sec-direct-sum"], "ptx/worksheet-gen-eigen.ptx": ["worksheet-gen-eigen"], "ptx/section_gen_eigen.ptx": ["sec-gen-eigen"], "ptx/section_jordan_form.ptx": ["sec-jordan-form"], "ptx/appendix-complex.ptx": ["appendix-complex-review"], "ptx/appendix_computation.ptx": ["ch-computation"], "ptx/section_jupyter.ptx": ["section-jupyter"], "ptx/section_python.ptx": ["sec-python-basics"], "ptx/section_sympy.ptx": ["sec-sympy"]}